CHANGELOG
LICENSE
MANIFEST.in
README.rst
buildout.cfg
setup.cfg
setup.py
tangled.sqlalchemy.egg-info/PKG-INFO
tangled.sqlalchemy.egg-info/SOURCES.txt
tangled.sqlalchemy.egg-info/dependency_links.txt
tangled.sqlalchemy.egg-info/requires.txt
tangled.sqlalchemy.egg-info/top_level.txt
tangled/sqlalchemy/__init__.py
tangled/sqlalchemy/tests.py