Metadata-Version: 1.1
Name: tangled.sqlalchemy
Version: 0.1a3
Summary: Tangled SQLAlchemy integration
Home-page: http://tangledframework.org/
Author: Wyatt Baldwin
Author-email: self@wyattbaldwin.com
License: UNKNOWN
Download-URL: https://github.com/TangledWeb/tangled.sqlalchemy/tags
Platform: UNKNOWN
Classifier: Development Status :: 3 - Alpha
Classifier: Intended Audience :: Developers
Classifier: License :: OSI Approved :: MIT License
Classifier: Programming Language :: Python :: 3
Classifier: Programming Language :: Python :: 3.3
Classifier: Programming Language :: Python :: 3.4
